virapi_plugins/openapi.py
virapi_plugins-0.1.0.dist-info/METADATA
virapi_plugins-0.1.0.dist-info/WHEEL
virapi_plugins-0.1.0.dist-info/top_level.txt
virapi_plugins-0.1.0.dist-info/RECORD
